__init__.py
keyboa/__init__.py
keyboa/base.py
keyboa/base_check.py
keyboa/button.py
keyboa/button_check.py
keyboa/constants.py
keyboa/functions_alignment.py
keyboa/functions_button_data.py
keyboa/functions_callback.py
keyboa/functions_precheck.py
keyboa/keyboard.py
keyboa/keyboards.py
keyboa-3.1.0.dist-info/LICENSE
keyboa-3.1.0.dist-info/METADATA
keyboa-3.1.0.dist-info/WHEEL
keyboa-3.1.0.dist-info/top_level.txt
keyboa-3.1.0.dist-info/RECORD
