Metadata-Version: 2.1
Name: keyboa
Version: 3.1.0
Summary: Telegram Inline Keyboards Generator
Home-page: https://github.com/torrua/keyboa
Author: torrua
Author-email: torrua@gmail.com
License: MIT
Download-URL: https://github.com/torrua/keyboa/archive/v3.1.0.tar.gz
Keywords: Generate,Inline,Keyboard,Telegram
Platform: UNKNOWN
Classifier: Development Status :: 5 - Production/Stable
Classifier: Intended Audience :: Developers
Classifier: Topic :: Software Development :: Build Tools
Classifier: License :: OSI Approved :: MIT License
Classifier: Programming Language :: Python :: 3.7
Classifier: Programming Language :: Python :: 3.8
Classifier: Programming Language :: Python :: 3.9
Requires-Python: >=3.7
License-File: LICENSE
